ts_sdk_connectors_python/__init__.py
ts_sdk_connectors_python/aws.py
ts_sdk_connectors_python/aws_factory.py
ts_sdk_connectors_python/certificate.py
ts_sdk_connectors_python/checksums.py
ts_sdk_connectors_python/client_creator.py
ts_sdk_connectors_python/command_listener.py
ts_sdk_connectors_python/config.py
ts_sdk_connectors_python/connector.py
ts_sdk_connectors_python/constants.py
ts_sdk_connectors_python/custom_commands.py
ts_sdk_connectors_python/event_emitter.py
ts_sdk_connectors_python/file_uploader/__init__.py
ts_sdk_connectors_python/file_uploader/_file_uploader.py
ts_sdk_connectors_python/file_uploader/models.py
ts_sdk_connectors_python/logger/__init__.py
ts_sdk_connectors_python/logger/_async_logging_utils.py
ts_sdk_connectors_python/logger/_base.py
ts_sdk_connectors_python/logger/_buffer.py
ts_sdk_connectors_python/logger/_cloudwatch.py
ts_sdk_connectors_python/logger/_cloudwatch_utils.py
ts_sdk_connectors_python/logger/_root.py
ts_sdk_connectors_python/manifest.py
ts_sdk_connectors_python/metrics.py
ts_sdk_connectors_python/models.py
ts_sdk_connectors_python/openapi_codegen/.gitignore
ts_sdk_connectors_python/openapi_codegen/README.md
ts_sdk_connectors_python/openapi_codegen/connectors_api_client/__init__.py
ts_sdk_connectors_python/openapi_codegen/connectors_api_client/api/__init__.py
ts_sdk_connectors_python/openapi_codegen/connectors_api_client/api/artifacts/__init__.py
ts_sdk_connectors_python/openapi_codegen/connectors_api_client/api/artifacts/artifact_controller_get_all.py
ts_sdk_connectors_python/openapi_codegen/connectors_api_client/api/artifacts/artifact_controller_get_by_id.py
ts_sdk_connectors_python/openapi_codegen/connectors_api_client/api/connectors/__init__.py
ts_sdk_connectors_python/openapi_codegen/connectors_api_client/api/connectors/connector_controller_check_config.py
ts_sdk_connectors_python/openapi_codegen/connectors_api_client/api/connectors/connector_controller_create.py
ts_sdk_connectors_python-2.0.0.dist-info/LICENSE.txt
ts_sdk_connectors_python-2.0.0.dist-info/METADATA
ts_sdk_connectors_python-2.0.0.dist-info/WHEEL
ts_sdk_connectors_python-2.0.0.dist-info/RECORD
