Metadata-Version: 2.3
Name: ts-sdk-connectors-python
Version: 2.0.0
Summary: ts-sdk-connectors-python
Author: TetraScience
Requires-Python: >=3.11,<3.12
Classifier: Programming Language :: Python :: 3
Classifier: Programming Language :: Python :: 3.11
Requires-Dist: aioboto3 (>=14.2.0,<15.0.0)
Requires-Dist: boto3-stubs[s3] (>=1.36.1,<2.0.0)
Requires-Dist: openapi-python-client (==0.24.0)
Requires-Dist: psutil (>=6.1.1,<7.0.0)
Requires-Dist: pydantic (>=2.10.4,<3.0.0)
Requires-Dist: types-aioboto3-lite[cloudwatch,logs,s3,sqs,ssm] (>=14.2.0,<15.0.0)
